cifsdk_zyre/__init__.py
cifsdk_zyre/_version.py
cifsdk_zyre/client.py
cifsdk_zyre-0.0.0a3.dist-info/DESCRIPTION.rst
cifsdk_zyre-0.0.0a3.dist-info/METADATA
cifsdk_zyre-0.0.0a3.dist-info/RECORD
cifsdk_zyre-0.0.0a3.dist-info/WHEEL
cifsdk_zyre-0.0.0a3.dist-info/entry_points.txt
cifsdk_zyre-0.0.0a3.dist-info/metadata.json
cifsdk_zyre-0.0.0a3.dist-info/top_level.txt
test/__init__.py
test/test_basic.py
