Metadata-Version: 2.0
Name: cifsdk-zyre
Version: 0.0.0a3
Summary: CIF Zyre Connector Framework
Home-page: https://github.com/csirtgadgets/cifsdk-zyre-py
Author: Wes Young
Author-email: wes@csirtgadgets.org
License: LGPL3
Keywords: security
Platform: UNKNOWN
Classifier: Topic :: System :: Networking
Classifier: Environment :: Other Environment
Classifier: Intended Audience :: Developers
Classifier: License :: OSI Approved :: GNU Lesser General Public License v3 (LGPLv3)
Classifier: Programming Language :: Python
Requires-Dist: cifsdk
Requires-Dist: csirtg-indicator
Requires-Dist: cython (>=0.20)
Requires-Dist: pyzmq
Requires-Dist: pyzyre
